espei/__init__.py
espei/analysis.py
espei/citing.py
espei/core_utils.py
espei/database_utils.py
espei/datasets.py
espei/espei_script.py
espei/input-schema.yaml
espei/logger.py
espei/paramselect.py
espei/phase_models.py
espei/plot.py
espei/priors.py
espei/refdata.py
espei/rstate.py
espei/shadow_functions.py
espei/sublattice_tools.py
espei/typing.py
espei/utils.py
espei/validation.py
espei/error_functions/__init__.py
espei/error_functions/activity_error.py
espei/error_functions/context.py
espei/error_functions/equilibrium_thermochemical_error.py
espei/error_functions/non_equilibrium_thermochemical_error.py
espei/error_functions/residual_base.py
espei/error_functions/zpf_error.py
espei/optimizers/__init__.py
espei/optimizers/opt_base.py
espei/optimizers/opt_mcmc.py
espei/optimizers/opt_scipy.py
espei/optimizers/utils.py
espei/parameter_selection/__init__.py
espei/parameter_selection/fitting_descriptions.py
espei/parameter_selection/fitting_steps.py
espei/parameter_selection/model_building.py
espei/parameter_selection/redlich_kister.py
espei/parameter_selection/selection.py
espei-0.9.0.dist-info/LICENSE
espei-0.9.0.dist-info/METADATA
espei-0.9.0.dist-info/WHEEL
espei-0.9.0.dist-info/entry_points.txt
espei-0.9.0.dist-info/top_level.txt
espei-0.9.0.dist-info/RECORD
