Metadata-Version: 2.1
Name: espei
Version: 0.9.0
Summary: Fitting thermodynamic models with pycalphad.
Home-page: https://espei.org/
Author: Brandon Bocklund
Author-email: brandonbocklund@gmail.com
License: MIT
Classifier: Development Status :: 4 - Beta
Classifier: Intended Audience :: Science/Research
Classifier: Topic :: Scientific/Engineering :: Physics
Classifier: Topic :: Scientific/Engineering :: Chemistry
Classifier: License :: OSI Approved :: MIT License
Classifier: Programming Language :: Python :: 3
Classifier: Programming Language :: Python :: 3.9
Classifier: Programming Language :: Python :: 3.10
Classifier: Programming Language :: Python :: 3.11
Classifier: Programming Language :: Python :: 3.12
License-File: LICENSE
Requires-Dist: cerberus
Requires-Dist: corner
Requires-Dist: dask[complete]>=2
Requires-Dist: distributed>=2
Requires-Dist: emcee<3
Requires-Dist: matplotlib
Requires-Dist: numpy>=1.20
Requires-Dist: pycalphad>=0.11.0
Requires-Dist: pydantic>2.0
Requires-Dist: pyyaml
Requires-Dist: setuptools-scm[toml]>=6.0
Requires-Dist: scikit-learn>=1.0
Requires-Dist: scipy
Requires-Dist: symengine>=0.9
Requires-Dist: tinydb>=4
Provides-Extra: dev
Requires-Dist: furo; extra == "dev"
Requires-Dist: ipython; extra == "dev"
Requires-Dist: pytest; extra == "dev"
Requires-Dist: sphinx; extra == "dev"
Requires-Dist: twine; extra == "dev"
Provides-Extra: mpi
Requires-Dist: mpi4py; extra == "mpi"
Requires-Dist: dask-mpi>=2; extra == "mpi"
